<?xml version='1.0' encoding='us-ascii'?>
<problem xmlns="http://www.w3schools.com" xmlns:xsi="http://www.w3.org/2001/XMLSchema-instance" xsi:schemaLocation="http://www.w3schools.com vrp_xml_schema.xsd"><problemType><fleetSize>FINITE</fleetSize></problemType><vehicles><vehicle><id>0</id><typeId>1</typeId><startLocation><index>0</index><id>0</id><coord x="13.5118284" y="55.775170300000006" /></startLocation><endLocation><index>32</index><id>32</id><coord x="13.865076402835975" y="55.75315086146599" /></endLocation><timeSchedule><start>38804.0</start><end>1.7976931348623157E308</end></timeSchedule><returnToDepot>true</returnToDepot></vehicle><vehicle><id>1</id><typeId>1</typeId><startLocation><index>1</index><id>1</id><coord x="13.9845862" y="55.5257191" /></startLocation><endLocation><index>33</index><id>33</id><coord x="13.760008648638264" y="55.44285480442536" /></endLocation><timeSchedule><start>38187.0</start><end>1.7976931348623157E308</end></timeSchedule><returnToDepot>true</returnToDepot></vehicle></vehicles><vehicleTypes><type><id>0</id><capacity-dimensions><dimension index="0">8</dimension><dimension index="1">1</dimension></capacity-dimensions><costs><distance>1.0</distance><time>0.5</time><fixed>500</fixed><wait>0.5</wait></costs></type><type><id>1</id><capacity-dimensions><dimension index="0">8</dimension><dimension index="1">1</dimension></capacity-dimensions><costs><distance>1.0</distance><time>0.5</time><fixed>500</fixed><wait>0.5</wait></costs></type><type><id>2</id><capacity-dimensions><dimension index="0">8</dimension><dimension index="1">1</dimension></capacity-dimensions><costs><distance>1.0</distance><time>0.5</time><fixed>500</fixed><wait>0.5</wait></costs></type><type><id>3</id><capacity-dimensions><dimension index="0">8</dimension><dimension index="1">1</dimension></capacity-dimensions><costs><distance>1.0</distance><time>0.5</time><fixed>500</fixed><wait>0.5</wait></costs></type><type><id>4</id><capacity-dimensions><dimension index="0">8</dimension><dimension index="1">1</dimension></capacity-dimensions><costs><distance>1.0</distance><time>0.5</time><fixed>500</fixed><wait>0.5</wait></costs></type></vehicleTypes><services><service id="16" type="delivery"><location><index>24</index><id>24</id><coord x="13.462125738319296" y="55.76011992430232" /></location><duration>10</duration><capacity-dimensions><dimension index="0">1</dimension><dimension index="1">0</dimension></capacity-dimensions><timeWindows><timeWindow><start>9671.271918</start><end>40890.221861</end></timeWindow></timeWindows></service><service id="45" type="delivery"><location><index>29</index><id>29</id><coord x="13.746646908708241" y="55.79220702444857" /></location><duration>10</duration><capacity-dimensions><dimension index="0">1</dimension><dimension index="1">1</dimension></capacity-dimensions><timeWindows><timeWindow><start>8452.576927</start><end>72523.889444</end></timeWindow></timeWindows></service><service id="43" type="delivery"><location><index>25</index><id>25</id><coord x="14.156947067670204" y="55.69663312162085" /></location><duration>10</duration><capacity-dimensions><dimension index="0">1</dimension><dimension index="1">0</dimension></capacity-dimensions><timeWindows><timeWindow><start>24909.867347</start><end>51650.341735</end></timeWindow></timeWindows></service><service id="1" type="delivery"><location><index>17</index><id>17</id><coord x="14.147284628222494" y="55.57935187731632" /></location><duration>10</duration><capacity-dimensions><dimension index="0">1</dimension><dimension index="1">1</dimension></capacity-dimensions><timeWindows><timeWindow><start>27449.538397</start><end>52828.786221</end></timeWindow></timeWindows></service></services><shipments><shipment id="6"><pickup><location><index>3</index><id>3</id><coord x="13.47552901146368" y="55.64920480826014" /></location><duration>30</duration><timeWindows><timeWindow><start>11561.450084</start><end>65796.87079</end></timeWindow></timeWindows></pickup><delivery><location><index>18</index><id>18</id><coord x="13.61093490718998" y="55.56423818611991" /></location><duration>10</duration><timeWindows><timeWindow><start>11561.450084</start><end>65796.87079</end></timeWindow></timeWindows></delivery><capacity-dimensions><dimension index="0">1</dimension><dimension index="1">0</dimension></capacity-dimensions></shipment><shipment id="30"><pickup><location><index>4</index><id>4</id><coord x="13.81164573236544" y="55.80570670540689" /></location><duration>30</duration><timeWindows><timeWindow><start>38148.153773</start><end>60561.293316</end></timeWindow></timeWindows></pickup><delivery><location><index>19</index><id>19</id><coord x="13.689551896919653" y="55.505730131483126" /></location><duration>10</duration><timeWindows><timeWindow><start>38148.153773</start><end>60561.293316</end></timeWindow></timeWindows></delivery><capacity-dimensions><dimension index="0">1</dimension><dimension index="1">0</dimension></capacity-dimensions></shipment><shipment id="2"><pickup><location><index>5</index><id>5</id><coord x="13.466650708420795" y="55.37759866184769" /></location><duration>30</duration><timeWindows><timeWindow><start>22815.437057</start><end>57938.240453</end></timeWindow></timeWindows></pickup><delivery><location><index>20</index><id>20</id><coord x="13.653558724520343" y="55.548133929169175" /></location><duration>10</duration><timeWindows><timeWindow><start>22815.437057</start><end>57938.240453</end></timeWindow></timeWindows></delivery><capacity-dimensions><dimension index="0">1</dimension><dimension index="1">0</dimension></capacity-dimensions></shipment><shipment id="31"><pickup><location><index>6</index><id>6</id><coord x="13.452042809893442" y="55.3819908756023" /></location><duration>30</duration><timeWindows><timeWindow><start>36419.25706</start><end>53356.628555</end></timeWindow></timeWindows></pickup><delivery><location><index>21</index><id>21</id><coord x="13.881623487515963" y="55.65288599514043" /></location><duration>10</duration><timeWindows><timeWindow><start>36419.25706</start><end>53356.628555</end></timeWindow></timeWindows></delivery><capacity-dimensions><dimension index="0">1</dimension><dimension index="1">0</dimension></capacity-dimensions></shipment><shipment id="23"><pickup><location><index>7</index><id>7</id><coord x="13.650068404603196" y="55.52765273215822" /></location><duration>30</duration><timeWindows><timeWindow><start>27245.844298</start><end>80151.756391</end></timeWindow></timeWindows></pickup><delivery><location><index>22</index><id>22</id><coord x="13.777982910404315" y="55.816126664454345" /></location><duration>10</duration><timeWindows><timeWindow><start>27245.844298</start><end>80151.756391</end></timeWindow></timeWindows></delivery><capacity-dimensions><dimension index="0">1</dimension><dimension index="1">0</dimension></capacity-dimensions></shipment><shipment id="14"><pickup><location><index>8</index><id>8</id><coord x="13.548826884882152" y="55.48410311176557" /></location><duration>30</duration><timeWindows><timeWindow><start>23712.131968</start><end>62978.066349</end></timeWindow></timeWindows></pickup><delivery><location><index>23</index><id>23</id><coord x="13.597850241790397" y="55.39653158496362" /></location><duration>10</duration><timeWindows><timeWindow><start>23712.131968</start><end>62978.066349</end></timeWindow></timeWindows></delivery><capacity-dimensions><dimension index="0">1</dimension><dimension index="1">0</dimension></capacity-dimensions></shipment><shipment id="44"><pickup><location><index>11</index><id>11</id><coord x="13.844860146305248" y="55.47218794754201" /></location><duration>30</duration><timeWindows><timeWindow><start>23385.233488</start><end>67695.754183</end></timeWindow></timeWindows></pickup><delivery><location><index>26</index><id>26</id><coord x="13.710882608143224" y="55.809083305313074" /></location><duration>10</duration><timeWindows><timeWindow><start>23385.233488</start><end>67695.754183</end></timeWindow></timeWindows></delivery><capacity-dimensions><dimension index="0">1</dimension><dimension index="1">1</dimension></capacity-dimensions></shipment><shipment id="35"><pickup><location><index>12</index><id>12</id><coord x="13.973908167733198" y="55.52533642517448" /></location><duration>30</duration><timeWindows><timeWindow><start>22953.183099</start><end>50386.441222</end></timeWindow></timeWindows></pickup><delivery><location><index>27</index><id>27</id><coord x="13.461691521274462" y="55.48193321811461" /></location><duration>10</duration><timeWindows><timeWindow><start>22953.183099</start><end>50386.441222</end></timeWindow></timeWindows></delivery><capacity-dimensions><dimension index="0">1</dimension><dimension index="1">0</dimension></capacity-dimensions></shipment><shipment id="5"><pickup><location><index>13</index><id>13</id><coord x="13.854502003492273" y="55.81819533701339" /></location><duration>30</duration><timeWindows><timeWindow><start>32254.166663</start><end>80718.631697</end></timeWindow></timeWindows></pickup><delivery><location><index>28</index><id>28</id><coord x="14.01630044088111" y="55.51027541003266" /></location><duration>10</duration><timeWindows><timeWindow><start>32254.166663</start><end>80718.631697</end></timeWindow></timeWindows></delivery><capacity-dimensions><dimension index="0">1</dimension><dimension index="1">1</dimension></capacity-dimensions></shipment><shipment id="36"><pickup><location><index>15</index><id>15</id><coord x="13.51523115956855" y="55.397213012007555" /></location><duration>30</duration><timeWindows><timeWindow><start>23903.263657</start><end>77412.23161</end></timeWindow></timeWindows></pickup><delivery><location><index>30</index><id>30</id><coord x="13.924075714990657" y="55.74803074438637" /></location><duration>10</duration><timeWindows><timeWindow><start>23903.263657</start><end>77412.23161</end></timeWindow></timeWindows></delivery><capacity-dimensions><dimension index="0">1</dimension><dimension index="1">1</dimension></capacity-dimensions></shipment><shipment id="48"><pickup><location><index>16</index><id>16</id><coord x="13.481574547390805" y="55.717734188635376" /></location><duration>30</duration><timeWindows><timeWindow><start>38184.07891</start><end>82432.090338</end></timeWindow></timeWindows></pickup><delivery><location><index>31</index><id>31</id><coord x="13.703354486753499" y="55.668391066879096" /></location><duration>10</duration><timeWindows><timeWindow><start>38184.07891</start><end>82432.090338</end></timeWindow></timeWindows></delivery><capacity-dimensions><dimension index="0">1</dimension><dimension index="1">1</dimension></capacity-dimensions></shipment></shipments><initialRoutes><route><driverId>noDriver</driverId><vehicleId>0</vehicleId><start>38804.0</start><act type="delivery"><serviceId>16</serviceId></act><act type="pickupShipment"><shipmentId>6</shipmentId></act><act type="pickupShipment"><shipmentId>31</shipmentId></act><act type="deliverShipment"><shipmentId>6</shipmentId></act><act type="deliverShipment"><shipmentId>31</shipmentId></act><act type="pickupShipment"><shipmentId>30</shipmentId></act><act type="delivery"><serviceId>45</serviceId></act><act type="deliverShipment"><shipmentId>30</shipmentId></act><end>0.0</end></route><route><driverId>noDriver</driverId><vehicleId>1</vehicleId><start>38187.0</start><act type="delivery"><serviceId>43</serviceId></act><act type="delivery"><serviceId>1</serviceId></act><act type="pickupShipment"><shipmentId>35</shipmentId></act><act type="pickupShipment"><shipmentId>44</shipmentId></act><act type="pickupShipment"><shipmentId>14</shipmentId></act><act type="deliverShipment"><shipmentId>14</shipmentId></act><act type="pickupShipment"><shipmentId>2</shipmentId></act><act type="deliverShipment"><shipmentId>35</shipmentId></act><act type="deliverShipment"><shipmentId>2</shipmentId></act><act type="deliverShipment"><shipmentId>44</shipmentId></act><act type="pickupShipment"><shipmentId>23</shipmentId></act><act type="pickupShipment"><shipmentId>36</shipmentId></act><act type="deliverShipment"><shipmentId>36</shipmentId></act><act type="deliverShipment"><shipmentId>23</shipmentId></act><act type="pickupShipment"><shipmentId>5</shipmentId></act><act type="deliverShipment"><shipmentId>5</shipmentId></act><end>0.0</end></route></initialRoutes></problem>